base/__init__.py
base/base_crawler.py
config/__init__.py
config/base_config.py
config/db_config.py
media_platform/__init__.py
media_platform/bilibili/__init__.py
media_platform/bilibili/client.py
media_platform/bilibili/core.py
media_platform/bilibili/exception.py
media_platform/bilibili/field.py
media_platform/bilibili/help.py
media_platform/bilibili/login.py
media_platform/douyin/__init__.py
media_platform/douyin/client.py
media_platform/douyin/core.py
media_platform/douyin/exception.py
media_platform/douyin/field.py
media_platform/douyin/login.py
media_platform/kuaishou/__init__.py
media_platform/kuaishou/client.py
media_platform/kuaishou/core.py
media_platform/kuaishou/exception.py
media_platform/kuaishou/field.py
media_platform/kuaishou/graphql.py
media_platform/kuaishou/login.py
media_platform/weibo/__init__.py
media_platform/weibo/client.py
media_platform/weibo/core.py
media_platform/weibo/exception.py
media_platform/weibo/field.py
media_platform/weibo/help.py
media_platform/weibo/login.py
media_platform/xhs/__init__.py
media_platform/xhs/client.py
media_platform/xhs/core.py
media_platform/xhs/exception.py
media_platform/xhs/field.py
media_platform/xhs/help.py
media_platform/xhs/login.py
proxy/__init__.py
proxy/base_proxy.py
proxy/proxy_ip_pool.py
proxy/types.py
proxy/providers/__init__.py
proxy/providers/free_proxy_list_1.py
proxy/providers/free_proxy_list_2.py
proxy/providers/jishu_http_proxy.py
proxy/providers/kuaidl_proxy.py
store/__init__.py
store/bilibili/__init__.py
store/bilibili/bilibili_store_impl.py
store/bilibili/bilibili_store_sql.py
store/douyin/__init__.py
store/douyin/douyin_store_impl.py
store/douyin/douyin_store_sql.py
store/kuaishou/__init__.py
store/kuaishou/kuaishou_store_impl.py
store/kuaishou/kuaishou_store_sql.py
store/weibo/__init__.py
store/weibo/weibo_store_image.py
store/weibo/weibo_store_impl.py
store/weibo/weibo_store_sql.py
store/xhs/__init__.py
store/xhs/xhs_store_impl.py
store/xhs/xhs_store_sql.py
test/__init__.py
my_media_crawler-0.1.4.dist-info/LICENSE
my_media_crawler-0.1.4.dist-info/METADATA
my_media_crawler-0.1.4.dist-info/WHEEL
my_media_crawler-0.1.4.dist-info/top_level.txt
my_media_crawler-0.1.4.dist-info/RECORD
