Metadata-Version: 2.1
Name: my_media_crawler
Version: 0.1.4
Summary: Forked from media clawer
Home-page: https://github.com/JohnPion-Zhang/my-media-crawler
Author: Eli
Author-email: johnpion.zhang@gmail.com
Keywords: python
Classifier: Development Status :: 4 - Beta
Classifier: Intended Audience :: Developers
Classifier: License :: OSI Approved :: MIT License
Classifier: Programming Language :: Python :: 3
Classifier: Programming Language :: Python :: 3.10
Classifier: Programming Language :: Python :: 3.11
Classifier: Programming Language :: Python :: 3.12
Requires-Python: >=3.10
License-File: LICENSE
Requires-Dist: aiofiles ==23.2.1
Requires-Dist: aiomysql ==0.2.0
Requires-Dist: annotated-types ==0.6.0
Requires-Dist: anyio ==4.3.0
Requires-Dist: beautifulsoup4 ==4.12.3
Requires-Dist: build ==1.2.1
Requires-Dist: certifi ==2024.2.2
Requires-Dist: click ==8.1.7
Requires-Dist: fastapi ==0.110.2
Requires-Dist: greenlet ==3.0.3
Requires-Dist: h11 ==0.14.0
Requires-Dist: httpcore ==0.17.3
Requires-Dist: httpx ==0.24.0
Requires-Dist: idna ==3.7
Requires-Dist: numpy ==1.26.4
Requires-Dist: opencv-python ==4.9.0.80
Requires-Dist: packaging ==24.0
Requires-Dist: Pillow ==9.5.0
Requires-Dist: playwright ==1.42.0
Requires-Dist: pydantic ==2.5.2
Requires-Dist: pydantic-core ==2.14.5
Requires-Dist: pyee ==11.0.1
Requires-Dist: PyExecJS ==1.5.1
Requires-Dist: PyMySQL ==1.1.0
Requires-Dist: pyproject-hooks ==1.1.0
Requires-Dist: redis ==4.6.0
Requires-Dist: setuptools ==69.2.0
Requires-Dist: six ==1.16.0
Requires-Dist: sniffio ==1.3.1
Requires-Dist: soupsieve ==2.5
Requires-Dist: starlette ==0.37.2
Requires-Dist: tenacity ==8.2.2
Requires-Dist: typing-extensions ==4.11.0
Requires-Dist: uvicorn ==0.29.0
Requires-Dist: wheel ==0.43.0
